sana/__init__.py
sana/base.py
sana/plot.py
sana-0.1.0.dist-info/DESCRIPTION.rst
sana-0.1.0.dist-info/METADATA
sana-0.1.0.dist-info/RECORD
sana-0.1.0.dist-info/WHEEL
sana-0.1.0.dist-info/metadata.json
sana-0.1.0.dist-info/top_level.txt
