Metadata-Version: 2.0
Name: sana
Version: 0.1.0
Summary: Sana  is for distance matrix similarity analysis in python / numpy / tensorflow
Home-page: https://github.com/jooh/sana
Author: Johan Carlin
Author-email: johan.carlin@gmail.com
License: MIT license
Keywords: sana
Platform: UNKNOWN
Classifier: Development Status :: 2 - Pre-Alpha
Classifier: Intended Audience :: Developers
Classifier: License :: OSI Approved :: MIT License
Classifier: Natural Language :: English
Classifier: Programming Language :: Python :: 3.6
Requires-Dist: numpy
